hexswitch/__init__.py
hexswitch/app.py
hexswitch/runtime.py
hexswitch/service.py
hexswitch/adapters/__init__.py
hexswitch/adapters/base.py
hexswitch/adapters/exceptions.py
hexswitch/adapters/grpc/_Grpc_Envelope.py
hexswitch/adapters/grpc/__init__.py
hexswitch/adapters/grpc/inbound_adapter.py
hexswitch/adapters/grpc/outbound_adapter.py
hexswitch/adapters/http/_Http_Envelope.py
hexswitch/adapters/http/__init__.py
hexswitch/adapters/http/fastapi_adapter.py
hexswitch/adapters/http/inbound_adapter.py
hexswitch/adapters/http/outbound_adapter.py
hexswitch/adapters/mcp/__init__.py
hexswitch/adapters/mcp/inbound_adapter.py
hexswitch/adapters/mcp/outbound_adapter.py
hexswitch/adapters/nats/_Nats_Envelope.py
hexswitch/adapters/nats/__init__.py
hexswitch/adapters/nats/inbound_adapter.py
hexswitch/adapters/nats/outbound_adapter.py
hexswitch/adapters/websocket/_WebSocket_Envelope.py
hexswitch/adapters/websocket/__init__.py
hexswitch/adapters/websocket/inbound_adapter.py
hexswitch/adapters/websocket/outbound_adapter.py
hexswitch/domain/__init__.py
hexswitch/domain/repositories/__init__.py
hexswitch/domain/repositories/base_repository.py
hexswitch/domain/services/__init__.py
hexswitch/domain/services/base_service.py
hexswitch/execution/__init__.py
hexswitch/execution/runner.py
hexswitch/gui/__init__.py
hexswitch/gui/routes.py
hexswitch/gui/server.py
hexswitch/handlers/__init__.py
hexswitch/handlers/health.py
hexswitch/handlers/loader.py
hexswitch/handlers/metrics.py
hexswitch/pipeline/__init__.py
hexswitch/pipeline/pipeline.py
hexswitch/pipeline/middleware/__init__.py
hexswitch/pipeline/middleware/backpressure.py
hexswitch/pipeline/middleware/base.py
hexswitch/pipeline/middleware/observability.py
hexswitch/pipeline/middleware/retry.py
hexswitch/pipeline/middleware/timeout.py
hexswitch/pipeline/middleware/trace.py
hexswitch/ports/__init__.py
hexswitch/ports/decorators.py
hexswitch/ports/exceptions.py
hexswitch/ports/outbound_registry.py
hexswitch/ports/port.py
hexswitch-0.1.3.dist-info/licenses/LICENSE
hexswitch-0.1.3.dist-info/METADATA
hexswitch-0.1.3.dist-info/WHEEL
hexswitch-0.1.3.dist-info/entry_points.txt
hexswitch-0.1.3.dist-info/top_level.txt
hexswitch-0.1.3.dist-info/RECORD
