Metadata-Version: 2.4
Name: hexswitch
Version: 0.1.3
Summary: Hexagonal runtime switchboard for config-driven microservices
Author: HexSwitch Contributors
License: MIT
Project-URL: Homepage, https://r0bes.github.io/hexSwitch/
Project-URL: Documentation, https://r0bes.github.io/hexSwitch/
Project-URL: Repository, https://github.com/R0bes/hexSwitch
Project-URL: Issues, https://github.com/R0bes/hexSwitch/issues
Keywords: hexagonal-architecture,microservices,runtime,adapter-pattern,ports-adapters,http,grpc,websocket,mcp,fastapi,opentelemetry
Classifier: Development Status :: 3 - Alpha
Classifier: Intended Audience :: Developers
Classifier: License :: OSI Approved :: MIT License
Classifier: Programming Language :: Python :: 3
Classifier: Programming Language :: Python :: 3.12
Classifier: Programming Language :: Python :: 3.13
Classifier: Topic :: Software Development :: Libraries :: Python Modules
Classifier: Topic :: Internet :: WWW/HTTP :: HTTP Servers
Classifier: Topic :: System :: Networking
Requires-Python: >=3.12
License-File: LICENSE
Requires-Dist: requests>=2.31.0
Requires-Dist: grpcio>=1.60.0
Requires-Dist: grpcio-tools>=1.60.0
Requires-Dist: websockets>=12.0
Requires-Dist: opentelemetry-api>=1.20.0
Requires-Dist: opentelemetry-sdk>=1.20.0
Requires-Dist: opentelemetry-exporter-otlp>=1.20.0
Requires-Dist: opentelemetry-semantic-conventions>=0.60b0
Requires-Dist: opentelemetry-instrumentation-fastapi>=0.42b0
Requires-Dist: fastapi>=0.104.0
Requires-Dist: httpx>=0.25.0
Requires-Dist: uvicorn[standard]>=0.24.0
Requires-Dist: pydantic>=2.5.0
Requires-Dist: nats-py>=2.6.0
Provides-Extra: dev
Requires-Dist: ruff>=0.1.0; extra == "dev"
Requires-Dist: pytest>=7.4.0; extra == "dev"
Requires-Dist: pytest-asyncio>=0.21.0; extra == "dev"
Requires-Dist: pytest-cov>=4.1.0; extra == "dev"
Requires-Dist: pytest-timeout>=2.1.0; extra == "dev"
Requires-Dist: pytest-order>=1.0.0; extra == "dev"
Requires-Dist: pytest-xdist>=3.0.0; extra == "dev"
Requires-Dist: mypy>=1.5.0; extra == "dev"
Requires-Dist: radon>=6.0.0; extra == "dev"
Requires-Dist: typer>=0.9.0; extra == "dev"
Requires-Dist: tomli>=2.0.0; python_version < "3.11" and extra == "dev"
Requires-Dist: tomli-w>=1.0.0; extra == "dev"
Dynamic: license-file
